
[
  {"id": 1, "Image": "files/img/01.jpg", "Title": "Jurek Ruppe", "Content": "Spray – Belalp"},
  {"id": 2, "Image": "files/img/02.jpg", "Title": "Nicolas Müller", "Content": "Backside Air"},
  {"id": 3, "Image": "files/img/03.jpg", "Title": "Rider unbekannt", "Content": "Powder in the air! – Wallis"},
  {"id": 4, "Image": "files/img/04.jpg", "Title": "Jeremiah Schwery", "Content": "Frontside 360"},
  {"id": 5, "Image": "files/img/05.jpg", "Title": "Nicolas Müller", "Content": "Powder Turn"},
  {"id": 6, "Image": "files/img/06.jpg", "Title": "Nicolas Müller", "Content": "Powder slide"},
  {"id": 7, "Image": "files/img/07.jpg", "Title": "Rider unbekannt", "Content": "Drop, Drop, Drop"}


]

